mu_pipelines_destination_spark/__init__.py
mu_pipelines_destination_spark/context/__init__.py
mu_pipelines_destination_spark/context/spark_context.py
mu_pipelines_destination_spark/destination_csv/__init__.py
mu_pipelines_destination_spark/destination_csv/destination_csv.py
mu_pipelines_destination_spark/destination_default_catalog/__init__.py
mu_pipelines_destination_spark/destination_default_catalog/destination_default_catalog.py
mu_pipelines_destination_spark/print/__init__.py
mu_pipelines_destination_spark/print/print.py
mu_pipelines_destination_spark/save_to_csv/__init__.py
mu_pipelines_destination_spark/save_to_csv/save_to_csv.py
mu_pipelines_destination_spark/save_to_table/__init__.py
mu_pipelines_destination_spark/save_to_table/save_to_table.py
mu_pipelines_destination_spark-0.2.0.dist-info/entry_points.txt
mu_pipelines_destination_spark-0.2.0.dist-info/licenses/LICENSE
mu_pipelines_destination_spark-0.2.0.dist-info/WHEEL
mu_pipelines_destination_spark-0.2.0.dist-info/METADATA
mu_pipelines_destination_spark-0.2.0.dist-info/RECORD
