Metadata-Version: 2.4
Name: mu_pipelines_destination_spark
Version: 0.2.0
Summary: mu_pipelines_destination_spark
Keywords: data movement,spark,etl
Author-email: MosaicSoft <mupipelines@gmail.com>
Requires-Python: >=3.11
Classifier: Programming Language :: Python :: 3
License-File: LICENSE
Requires-Dist: deprecation >=2.0.6
Requires-Dist: mu-pipelines-interfaces >=0.1.4
Requires-Dist: pyspark >=3.5.0
Project-URL: documentation, https://mosaicsoft-data.github.io/mu-pipelines-doc/
